crimson/folder_system/__init__.py
crimson/folder_system/delete.py
crimson/folder_system/filter.py
crimson/folder_system/path.py
crimson/folder_system/search.py
crimson_folder_system-0.1.4.dist-info/LICENSE
crimson_folder_system-0.1.4.dist-info/METADATA
crimson_folder_system-0.1.4.dist-info/WHEEL
crimson_folder_system-0.1.4.dist-info/top_level.txt
crimson_folder_system-0.1.4.dist-info/RECORD
